gingerfy/__init__.py
gingerfy/main.py
gingerfy/src/__init__.py
gingerfy/src/gingerfied.py
gingerfy/src/gingerfier.py
gingerfy/src/unginger.py
gingerfy-0.1.0b0.dist-info/METADATA
gingerfy-0.1.0b0.dist-info/RECORD
gingerfy-0.1.0b0.dist-info/WHEEL
gingerfy-0.1.0b0.dist-info/top_level.txt
