Metadata-Version: 2.1
Name: gingerfy
Version: 0.1.0b0
Summary: Remove broken colours from strings and replace them with the one true colour, GINGER!!
Home-page: http://github.com/RobDWaller/gingerfy
Author: RobDWaller
Author-email: rdwaller1984@googlemail.com
License: MIT
Platform: UNKNOWN
Classifier: Programming Language :: Python :: 3
Classifier: License :: OSI Approved :: MIT License
Classifier: Operating System :: OS Independent
